nvfuser_cu118_torch23-0.2.8.dev20240724.dist-info/WHEEL
nvfuser_cu118_torch23-0.2.8.dev20240724.dist-info/top_level.txt
nvfuser_cu118_torch23-0.2.8.dev20240724.dist-info/RECORD
nvfuser_cu118_torch23-0.2.8.dev20240724.dist-info/METADATA
nvfuser_cu118_torch23-0.2.8.dev20240724.dist-info/LICENSE
nvfuser/__init__.pyi
nvfuser/_C.cpython-310-x86_64-linux-gnu.so
nvfuser/utils.py
nvfuser/version.py
nvfuser/pytorch_utils.py
nvfuser/__init__.py
nvfuser/nvfuser_version.py
nvfuser/share/cmake/nvfuser/NvfuserConfig.cmake
nvfuser/share/cmake/nvfuser/NvfuserConfig-release.cmake
nvfuser/lib/libnvfuser_codegen.so
nvfuser/include/nvfuser/kernel.h
nvfuser/include/nvfuser/global_allocator.h
nvfuser/include/nvfuser/val_graph.h
nvfuser/include/nvfuser/dynamic_transform.h
nvfuser/include/nvfuser/index_compute.h
nvfuser/include/nvfuser/fusion_segmenter.h
nvfuser/include/nvfuser/kernel_ir.h
nvfuser/include/nvfuser/non_divisible_split.h
nvfuser/include/nvfuser/tma.h
nvfuser/include/nvfuser/mma_type.h
nvfuser/include/nvfuser/expr_evaluator.h
nvfuser/include/nvfuser/maxinfo_propagator.h
nvfuser/include/nvfuser/executor.h
nvfuser/include/nvfuser/compute_at_map.h
nvfuser/include/nvfuser/visibility.h
nvfuser/include/nvfuser/sys_utils.h
nvfuser/include/nvfuser/iter_visitor.h
nvfuser/include/nvfuser/tensor_metadata.h
nvfuser/include/nvfuser/vectorization_info.h
nvfuser/include/nvfuser/opaque_type.h
nvfuser/include/nvfuser/logical_domain_map.h
nvfuser/include/nvfuser/inlining.h
nvfuser/include/nvfuser/validator_utils.h
nvfuser/include/nvfuser/kernel_cache.h
nvfuser/include/nvfuser/cuda_utils.h
nvfuser/include/nvfuser/evaluator_common.h
nvfuser/include/nvfuser/fusion.h
nvfuser/include/nvfuser/executor_kernel_arg.h
nvfuser/include/nvfuser/transform_replay.h
nvfuser/include/nvfuser/options.h
nvfuser/include/nvfuser/parallel_dimension_map.h
nvfuser/include/nvfuser/debug.h
nvfuser/include/nvfuser/instrumentation.h
nvfuser/include/nvfuser/alias_analysis.h
nvfuser/include/nvfuser/parallel_type_bitmap.h
nvfuser/include/nvfuser/grouped_reduction.h
nvfuser/include/nvfuser/disjoint_set.h
nvfuser/include/nvfuser/type.h
nvfuser/include/nvfuser/predicate_compute.h
nvfuser/include/nvfuser/swizzle.h
nvfuser/include/nvfuser/executor_utils.h
